test_pypi_pri/__init__.py
test_pypi_pri/mars.py
test_pypi_pri-0.1.0.dist-info/METADATA
test_pypi_pri-0.1.0.dist-info/WHEEL
test_pypi_pri-0.1.0.dist-info/RECORD
